flowutils/__init__.py
flowutils/_version.py
flowutils/compensate.py
flowutils/gating.py
flowutils/gating_c.cpython-312-aarch64-linux-gnu.so
flowutils/logicle_c.cpython-312-aarch64-linux-gnu.so
flowutils/transforms.py
flowutils-1.2.2.dist-info/METADATA
flowutils-1.2.2.dist-info/WHEEL
flowutils-1.2.2.dist-info/top_level.txt
flowutils-1.2.2.dist-info/RECORD
flowutils-1.2.2.dist-info/licenses/LICENSE
