Metadata-Version: 2.4
Name: FlowUtils
Version: 1.2.2
Summary: Flow Cytometry Standard Utilities
Home-page: https://github.com/whitews/flowutils
Author: Scott White
Author-email: whitews@gmail.com
License: BSD
Classifier: Programming Language :: Python :: 3.14
Classifier: Programming Language :: Python :: 3.13
Classifier: Programming Language :: Python :: 3.12
Classifier: Programming Language :: Python :: 3.11
Classifier: Programming Language :: Python :: 3.10
Classifier: Programming Language :: Python :: 3.9
License-File: LICENSE
Requires-Dist: numpy<3.0,>=2.0
Dynamic: author
Dynamic: author-email
Dynamic: classifier
Dynamic: description
Dynamic: description-content-type
Dynamic: home-page
Dynamic: license
Dynamic: license-file
Dynamic: requires-dist
Dynamic: summary
